{
    "trackLyrics": {
        "syncType": "UNSYNCED",
        "lines": [
            {
                "startTimeMs": "0",
                "words": "Lies, broken dreams, the dismal past",
                "syllables": []
            },
            {
                "startTimeMs": "0",
                "words": "Is there more than life I should know",
                "syllables": []
            },
            {
                "startTimeMs": "0",
                "words": "Ending wars, when in pain",
                "syllables": []
            },
            {
                "startTimeMs": "0",
                "words": "When in love, mankind is insane",
                "syllables": []
            },
            {
                "startTimeMs": "0",
                "words": "When there's all these possibilities",
                "syllables": []
            },
            {
                "startTimeMs": "0",
                "words": "Some will fail and some will achieve",
                "syllables": []
            },
            {
                "startTimeMs": "0",
                "words": "Even though in my youth",
                "syllables": []
            },
            {
                "startTimeMs": "0",
                "words": "I didn't know, but what can I do?",
                "syllables": []
            },
            {
                "startTimeMs": "0",
                "words": "And I may not ever see",
                "syllables": []
            },
            {
                "startTimeMs": "0",
                "words": "In my pain, my suffering",
                "syllables": []
            },
            {
                "startTimeMs": "0",
                "words": "Cannot live for the rest of my life",
                "syllables": []
            },
            {
                "startTimeMs": "0",
                "words": "D.N.R. do not resuscitate me",
                "syllables": []
            },
            {
                "startTimeMs": "0",
                "words": "♪",
                "syllables": []
            },
            {
                "startTimeMs": "0",
                "words": "Life, lost unseen, behind the mask",
                "syllables": []
            },
            {
                "startTimeMs": "0",
                "words": "And with open arms will I grasp",
                "syllables": []
            },
            {
                "startTimeMs": "0",
                "words": "Open doors, open minds",
                "syllables": []
            },
            {
                "startTimeMs": "0",
                "words": "Ending all the madness I hate",
                "syllables": []
            },
            {
                "startTimeMs": "0",
                "words": "And I may not ever see",
                "syllables": []
            },
            {
                "startTimeMs": "0",
                "words": "In my pain, my misery",
                "syllables": []
            },
            {
                "startTimeMs": "0",
                "words": "Cannot live for the rest of my life",
                "syllables": []
            },
            {
                "startTimeMs": "0",
                "words": "D.N.R. do not resuscitate me",
                "syllables": []
            },
            {
                "startTimeMs": "0",
                "words": "D.N.R.",
                "syllables": []
            },
            {
                "startTimeMs": "0",
                "words": "♪",
                "syllables": []
            },
            {
                "startTimeMs": "0",
                "words": "Wings of sadness will hold my prayers",
                "syllables": []
            },
            {
                "startTimeMs": "0",
                "words": "All this madness will end my fears",
                "syllables": []
            },
            {
                "startTimeMs": "0",
                "words": "Contempt in life, conceptualize",
                "syllables": []
            },
            {
                "startTimeMs": "0",
                "words": "Wrong or right, the ending of life",
                "syllables": []
            },
            {
                "startTimeMs": "0",
                "words": "God, save me now",
                "syllables": []
            },
            {
                "startTimeMs": "0",
                "words": "Time, end it now, no going back",
                "syllables": []
            },
            {
                "startTimeMs": "0",
                "words": "Can you see the light as you pass?",
                "syllables": []
            },
            {
                "startTimeMs": "0",
                "words": "Ending wars, when in pain",
                "syllables": []
            },
            {
                "startTimeMs": "0",
                "words": "Waiting all my life to be saved",
                "syllables": []
            },
            {
                "startTimeMs": "0",
                "words": "And I will not ever see",
                "syllables": []
            },
            {
                "startTimeMs": "0",
                "words": "All the pain and suffering",
                "syllables": []
            },
            {
                "startTimeMs": "0",
                "words": "Cannot live for the rest of my life",
                "syllables": []
            },
            {
                "startTimeMs": "0",
                "words": "D.N.R. do not resuscitate me",
                "syllables": []
            },
            {
                "startTimeMs": "0",
                "words": "D.N.R.",
                "syllables": []
            },
            {
                "startTimeMs": "0",
                "words": "",
                "syllables": []
            }
        ],
        "provider": "MusixMatch",
        "providerLyricsId": "791544",
        "providerDisplayName": "Musixmatch",
        "syncLyricsUri": "",
        "isDenseTypeface": false,
        "alternatives": [],
        "language": "en",
        "isRtlLanguage": false,
        "fullscreenAction": "FULLSCREEN_LYRICS"
    },
    "trackInfo": {
        "album": {
            "album_type": "album",
            "artists": [
                {
                    "external_urls": {
                        "spotify": "https://open.spotify.com/artist/28hJdGN1Awf7u3ifk2lVkg"
                    },
                    "href": "https://api.spotify.com/v1/artists/28hJdGN1Awf7u3ifk2lVkg",
                    "id": "28hJdGN1Awf7u3ifk2lVkg",
                    "name": "Testament",
                    "type": "artist",
                    "uri": "spotify:artist:28hJdGN1Awf7u3ifk2lVkg"
                }
            ],
            "external_urls": {
                "spotify": "https://open.spotify.com/album/0dYgfOuAerUldWRodoOR6J"
            },
            "href": "https://api.spotify.com/v1/albums/0dYgfOuAerUldWRodoOR6J",
            "id": "0dYgfOuAerUldWRodoOR6J",
            "images": [
                {
                    "height": 640,
                    "url": "https://i.scdn.co/image/ab67616d0000b273f1897a3debc7d085fcaa901c",
                    "width": 640
                },
                {
                    "height": 300,
                    "url": "https://i.scdn.co/image/ab67616d00001e02f1897a3debc7d085fcaa901c",
                    "width": 300
                },
                {
                    "height": 64,
                    "url": "https://i.scdn.co/image/ab67616d00004851f1897a3debc7d085fcaa901c",
                    "width": 64
                }
            ],
            "name": "The Gathering",
            "release_date": "1999-06-08",
            "release_date_precision": "day",
            "total_tracks": 12,
            "type": "album",
            "uri": "spotify:album:0dYgfOuAerUldWRodoOR6J"
        },
        "artists": [
            {
                "external_urls": {
                    "spotify": "https://open.spotify.com/artist/28hJdGN1Awf7u3ifk2lVkg"
                },
                "href": "https://api.spotify.com/v1/artists/28hJdGN1Awf7u3ifk2lVkg",
                "id": "28hJdGN1Awf7u3ifk2lVkg",
                "name": "Testament",
                "type": "artist",
                "uri": "spotify:artist:28hJdGN1Awf7u3ifk2lVkg"
            }
        ],
        "disc_number": 1,
        "duration_ms": 212493,
        "explicit": false,
        "external_ids": {
            "isrc": "DED831701409"
        },
        "external_urls": {
            "spotify": "https://open.spotify.com/track/15MwrEdteIbx0VZSJsXtia"
        },
        "href": "https://api.spotify.com/v1/tracks/15MwrEdteIbx0VZSJsXtia",
        "id": "15MwrEdteIbx0VZSJsXtia",
        "is_local": false,
        "name": "D.N.R. (Do Not Resuscitate)",
        "popularity": 49,
        "preview_url": "https://p.scdn.co/mp3-preview/ffef8eb37fc8c3d363ccb4b12f52b8eeb21932a2?cid=774b29d4f13844c495f206cafdad9c86",
        "track_number": 1,
        "type": "track",
        "uri": "spotify:track:15MwrEdteIbx0VZSJsXtia"
    }
}