{
    "trackLyrics": {
        "syncType": "UNSYNCED",
        "lines": [
            {
                "startTimeMs": "0",
                "words": "In the distant",
                "syllables": []
            },
            {
                "startTimeMs": "0",
                "words": "Far away",
                "syllables": []
            },
            {
                "startTimeMs": "0",
                "words": "Trying to figure it out",
                "syllables": []
            },
            {
                "startTimeMs": "0",
                "words": "But I can't explain",
                "syllables": []
            },
            {
                "startTimeMs": "0",
                "words": "Now we see it",
                "syllables": []
            },
            {
                "startTimeMs": "0",
                "words": "Now we don't",
                "syllables": []
            },
            {
                "startTimeMs": "0",
                "words": "We're floating around",
                "syllables": []
            },
            {
                "startTimeMs": "0",
                "words": "In the unknown zone",
                "syllables": []
            },
            {
                "startTimeMs": "0",
                "words": "Watch the starlight",
                "syllables": []
            },
            {
                "startTimeMs": "0",
                "words": "Shooting for the sky",
                "syllables": []
            },
            {
                "startTimeMs": "0",
                "words": "Reaching out to catch",
                "syllables": []
            },
            {
                "startTimeMs": "0",
                "words": "A piece of Paradise",
                "syllables": []
            },
            {
                "startTimeMs": "0",
                "words": "Is it true",
                "syllables": []
            },
            {
                "startTimeMs": "0",
                "words": "Or is this just imagination",
                "syllables": []
            },
            {
                "startTimeMs": "0",
                "words": "Visions twist around my mind",
                "syllables": []
            },
            {
                "startTimeMs": "0",
                "words": "And brings me shelter from the night",
                "syllables": []
            },
            {
                "startTimeMs": "0",
                "words": "Where do we go",
                "syllables": []
            },
            {
                "startTimeMs": "0",
                "words": "Where do we go from here",
                "syllables": []
            },
            {
                "startTimeMs": "0",
                "words": "When do we finally disappear",
                "syllables": []
            },
            {
                "startTimeMs": "0",
                "words": "Future world",
                "syllables": []
            },
            {
                "startTimeMs": "0",
                "words": "There's nothing left to save",
                "syllables": []
            },
            {
                "startTimeMs": "0",
                "words": "They blew it all away",
                "syllables": []
            },
            {
                "startTimeMs": "0",
                "words": "Future world",
                "syllables": []
            },
            {
                "startTimeMs": "0",
                "words": "Tonight we're riding on",
                "syllables": []
            },
            {
                "startTimeMs": "0",
                "words": "The final escape",
                "syllables": []
            },
            {
                "startTimeMs": "0",
                "words": "Is it heaven",
                "syllables": []
            },
            {
                "startTimeMs": "0",
                "words": "Is it hell",
                "syllables": []
            },
            {
                "startTimeMs": "0",
                "words": "Is it the afterworld",
                "syllables": []
            },
            {
                "startTimeMs": "0",
                "words": "Or just something else",
                "syllables": []
            },
            {
                "startTimeMs": "0",
                "words": "Are we prisoners in Nowhereland",
                "syllables": []
            },
            {
                "startTimeMs": "0",
                "words": "Where darkness is your only friend",
                "syllables": []
            },
            {
                "startTimeMs": "0",
                "words": "Kept inside this wall of sleep",
                "syllables": []
            },
            {
                "startTimeMs": "0",
                "words": "Have we fallen into a deep freeze",
                "syllables": []
            },
            {
                "startTimeMs": "0",
                "words": "Left the wastelands",
                "syllables": []
            },
            {
                "startTimeMs": "0",
                "words": "Broke the lines",
                "syllables": []
            },
            {
                "startTimeMs": "0",
                "words": "Crossed the border to another time",
                "syllables": []
            },
            {
                "startTimeMs": "0",
                "words": "Being drawn by the fates",
                "syllables": []
            },
            {
                "startTimeMs": "0",
                "words": "Who run our destinies",
                "syllables": []
            },
            {
                "startTimeMs": "0",
                "words": "Stranded in a state of life",
                "syllables": []
            },
            {
                "startTimeMs": "0",
                "words": "Where dreams become reality",
                "syllables": []
            },
            {
                "startTimeMs": "0",
                "words": "Where do we go",
                "syllables": []
            },
            {
                "startTimeMs": "0",
                "words": "Where do we go from here",
                "syllables": []
            },
            {
                "startTimeMs": "0",
                "words": "When do we finally disappear",
                "syllables": []
            },
            {
                "startTimeMs": "0",
                "words": "Future world",
                "syllables": []
            },
            {
                "startTimeMs": "0",
                "words": "There's nothing left to save",
                "syllables": []
            },
            {
                "startTimeMs": "0",
                "words": "They blew it all away",
                "syllables": []
            },
            {
                "startTimeMs": "0",
                "words": "Future world",
                "syllables": []
            },
            {
                "startTimeMs": "0",
                "words": "Tonight we're riding on",
                "syllables": []
            },
            {
                "startTimeMs": "0",
                "words": "The final escape",
                "syllables": []
            },
            {
                "startTimeMs": "0",
                "words": "In troubled times",
                "syllables": []
            },
            {
                "startTimeMs": "0",
                "words": "We saw the writing on the wall",
                "syllables": []
            },
            {
                "startTimeMs": "0",
                "words": "We heard the fools",
                "syllables": []
            },
            {
                "startTimeMs": "0",
                "words": "Who brought the human race to fall",
                "syllables": []
            },
            {
                "startTimeMs": "0",
                "words": "We'll build another generation",
                "syllables": []
            },
            {
                "startTimeMs": "0",
                "words": "And not destroy the God creation",
                "syllables": []
            },
            {
                "startTimeMs": "0",
                "words": "♪",
                "syllables": []
            },
            {
                "startTimeMs": "0",
                "words": "Future world",
                "syllables": []
            },
            {
                "startTimeMs": "0",
                "words": "There's nothing left to save",
                "syllables": []
            },
            {
                "startTimeMs": "0",
                "words": "They blew it all away",
                "syllables": []
            },
            {
                "startTimeMs": "0",
                "words": "Future world",
                "syllables": []
            },
            {
                "startTimeMs": "0",
                "words": "Tonight we're riding on",
                "syllables": []
            },
            {
                "startTimeMs": "0",
                "words": "The final escape",
                "syllables": []
            },
            {
                "startTimeMs": "0",
                "words": "Take your chances",
                "syllables": []
            },
            {
                "startTimeMs": "0",
                "words": "Turn the key",
                "syllables": []
            },
            {
                "startTimeMs": "0",
                "words": "Open up the doors",
                "syllables": []
            },
            {
                "startTimeMs": "0",
                "words": "To another history",
                "syllables": []
            },
            {
                "startTimeMs": "0",
                "words": "Here's no questions",
                "syllables": []
            },
            {
                "startTimeMs": "0",
                "words": "No demands",
                "syllables": []
            },
            {
                "startTimeMs": "0",
                "words": "Here's the future",
                "syllables": []
            },
            {
                "startTimeMs": "0",
                "words": "This is wonderland",
                "syllables": []
            },
            {
                "startTimeMs": "0",
                "words": "♪",
                "syllables": []
            },
            {
                "startTimeMs": "0",
                "words": "Oh oh",
                "syllables": []
            },
            {
                "startTimeMs": "0",
                "words": "Oh oh",
                "syllables": []
            },
            {
                "startTimeMs": "0",
                "words": "Oh oh",
                "syllables": []
            },
            {
                "startTimeMs": "0",
                "words": "Oh oh",
                "syllables": []
            },
            {
                "startTimeMs": "0",
                "words": "Oh oh",
                "syllables": []
            },
            {
                "startTimeMs": "0",
                "words": "Oh oh",
                "syllables": []
            },
            {
                "startTimeMs": "0",
                "words": "Oh oh",
                "syllables": []
            },
            {
                "startTimeMs": "0",
                "words": "Oh oh",
                "syllables": []
            },
            {
                "startTimeMs": "0",
                "words": "Oh oh",
                "syllables": []
            },
            {
                "startTimeMs": "0",
                "words": "Oh oh",
                "syllables": []
            },
            {
                "startTimeMs": "0",
                "words": "",
                "syllables": []
            }
        ],
        "provider": "MusixMatch",
        "providerLyricsId": "14906142",
        "providerDisplayName": "Musixmatch",
        "syncLyricsUri": "",
        "isDenseTypeface": false,
        "alternatives": [],
        "language": "en",
        "isRtlLanguage": false,
        "fullscreenAction": "FULLSCREEN_LYRICS"
    },
    "trackInfo": {
        "album": {
            "album_type": "album",
            "artists": [
                {
                    "external_urls": {
                        "spotify": "https://open.spotify.com/artist/4OGo8f0tdKloP3IZwvnLqt"
                    },
                    "href": "https://api.spotify.com/v1/artists/4OGo8f0tdKloP3IZwvnLqt",
                    "id": "4OGo8f0tdKloP3IZwvnLqt",
                    "name": "Pretty Maids",
                    "type": "artist",
                    "uri": "spotify:artist:4OGo8f0tdKloP3IZwvnLqt"
                }
            ],
            "external_urls": {
                "spotify": "https://open.spotify.com/album/5tzRyHhVzI9JbrRPlqOPLD"
            },
            "href": "https://api.spotify.com/v1/albums/5tzRyHhVzI9JbrRPlqOPLD",
            "id": "5tzRyHhVzI9JbrRPlqOPLD",
            "images": [
                {
                    "height": 640,
                    "url": "https://i.scdn.co/image/ab67616d0000b2738e63608fce44bcd03f9963cf",
                    "width": 640
                },
                {
                    "height": 300,
                    "url": "https://i.scdn.co/image/ab67616d00001e028e63608fce44bcd03f9963cf",
                    "width": 300
                },
                {
                    "height": 64,
                    "url": "https://i.scdn.co/image/ab67616d000048518e63608fce44bcd03f9963cf",
                    "width": 64
                }
            ],
            "name": "Future World",
            "release_date": "1987-04-07",
            "release_date_precision": "day",
            "total_tracks": 9,
            "type": "album",
            "uri": "spotify:album:5tzRyHhVzI9JbrRPlqOPLD"
        },
        "artists": [
            {
                "external_urls": {
                    "spotify": "https://open.spotify.com/artist/4OGo8f0tdKloP3IZwvnLqt"
                },
                "href": "https://api.spotify.com/v1/artists/4OGo8f0tdKloP3IZwvnLqt",
                "id": "4OGo8f0tdKloP3IZwvnLqt",
                "name": "Pretty Maids",
                "type": "artist",
                "uri": "spotify:artist:4OGo8f0tdKloP3IZwvnLqt"
            }
        ],
        "disc_number": 1,
        "duration_ms": 323960,
        "explicit": false,
        "external_ids": {
            "isrc": "DKAXG9028101"
        },
        "external_urls": {
            "spotify": "https://open.spotify.com/track/2v9855tCBy97Qp4BmMZscS"
        },
        "href": "https://api.spotify.com/v1/tracks/2v9855tCBy97Qp4BmMZscS",
        "id": "2v9855tCBy97Qp4BmMZscS",
        "is_local": false,
        "name": "Future World",
        "popularity": 44,
        "preview_url": "https://p.scdn.co/mp3-preview/6cc5a09400e57f5afd41756874281fd53001a923?cid=774b29d4f13844c495f206cafdad9c86",
        "track_number": 1,
        "type": "track",
        "uri": "spotify:track:2v9855tCBy97Qp4BmMZscS"
    }
}